ansible_doc_legalese/__init__.py
ansible_doc_legalese/cli.py
ansible_doc_legalese/formatter.py
ansible_doc_legalese-1.0.0.dist-info/licenses/LICENSE
ansible_doc_legalese-1.0.0.dist-info/METADATA
ansible_doc_legalese-1.0.0.dist-info/WHEEL
ansible_doc_legalese-1.0.0.dist-info/entry_points.txt
ansible_doc_legalese-1.0.0.dist-info/top_level.txt
ansible_doc_legalese-1.0.0.dist-info/RECORD
