Metadata-Version: 2.4
Name: ansible-doc-legalese
Version: 1.0.0
Summary: Transform Ansible documentation into legal court documents
Author-email: FrozenFOXX <frozenfoxx@cultoffoxx.net>
License-Expression: Apache-2.0
Project-URL: Homepage, https://github.com/frozenfoxx/ansible-doc-legalese
Project-URL: Repository, https://github.com/frozenfoxx/ansible-doc-legalese.git
Project-URL: Issues, https://github.com/frozenfoxx/ansible-doc-legalese/issues
Keywords: ansible,documentation,legalese,humor
Classifier: Development Status :: 5 - Production/Stable
Classifier: Environment :: Console
Classifier: Intended Audience :: Developers
Classifier: Intended Audience :: System Administrators
Classifier: Operating System :: OS Independent
Classifier: Programming Language :: Python :: 3
Classifier: Programming Language :: Python :: 3.8
Classifier: Programming Language :: Python :: 3.9
Classifier: Programming Language :: Python :: 3.10
Classifier: Programming Language :: Python :: 3.11
Classifier: Programming Language :: Python :: 3.12
Classifier: Topic :: Documentation
Classifier: Topic :: System :: Systems Administration
Classifier: Topic :: Utilities
Requires-Python: >=3.8
License-File: LICENSE
Provides-Extra: yaml
Requires-Dist: pyyaml>=5.0; extra == "yaml"
Provides-Extra: dev
Requires-Dist: pyyaml>=5.0; extra == "dev"
Requires-Dist: pytest>=7.0; extra == "dev"
Requires-Dist: pytest-cov>=4.0; extra == "dev"
Requires-Dist: black>=23.0; extra == "dev"
Requires-Dist: ruff>=0.1.0; extra == "dev"
Dynamic: license-file
